gin/__init__.py
gin/config.py
gin/config_parser.py
gin/selector_map.py
gin/utils.py
gin/testdata/__init__.py
gin/testdata/import_test_configurables.py
gin/testdata/invalid_import.py
gin/tf/__init__.py
gin/tf/external_configurables.py
gin/tf/utils.py
gin_config-0.3.0.dist-info/AUTHORS
gin_config-0.3.0.dist-info/LICENSE
gin_config-0.3.0.dist-info/METADATA
gin_config-0.3.0.dist-info/WHEEL
gin_config-0.3.0.dist-info/top_level.txt
gin_config-0.3.0.dist-info/RECORD
