Metadata-Version: 2.1
Name: gin-config
Version: 0.3.0
Summary: Gin-Config: A lightweight configuration library for Python
Home-page: https://github.com/google/gin-config
Author: The Gin-Config Team
License: Apache 2.0
Project-URL: Documentation, https://github.com/google/gin-config/docs
Project-URL: Bug Reports, https://github.com/google/gin-config/issues
Project-URL: Source, https://github.com/google/gin-config
Keywords: gin-config gin python configuration machine learning
Platform: UNKNOWN
Classifier: Development Status :: 3 - Alpha
Classifier: Intended Audience :: Developers
Classifier: Intended Audience :: Education
Classifier: Intended Audience :: Science/Research
Classifier: License :: OSI Approved :: Apache Software License
Classifier: Programming Language :: Python :: 2
Classifier: Programming Language :: Python :: 2.7
Classifier: Programming Language :: Python :: 3
Classifier: Programming Language :: Python :: 3.5
Classifier: Programming Language :: Python :: 3.6
Classifier: Programming Language :: Python :: 3.7
Classifier: Topic :: Scientific/Engineering
Classifier: Topic :: Scientific/Engineering :: Mathematics
Classifier: Topic :: Scientific/Engineering :: Artificial Intelligence
Classifier: Topic :: Software Development
Classifier: Topic :: Software Development :: Libraries
Classifier: Topic :: Software Development :: Libraries :: Python Modules
Provides-Extra: tensorflow
Provides-Extra: tensorflow-gpu
Provides-Extra: testing
Provides-Extra: tf-nightly
